var data_7 = {
  "type": "FeatureCollection",
  "features": [
    {
      "type": "Feature",
      "properties": {
        "﻿全国地方公共団体コード": "23230",
        "識別値": "POK001",
        "種別": "交番",
        "name": "岩崎交番",
        "施設名称（カナ）": "イワサキコウバン",
        "通称": "",
        "住所表記": "愛知県日進市岩崎町大塚45-3",
        "郵便番号": "4700131",
        "description": "交番への連絡は愛知警察署の交換（0561-39-0110）を通じて電話をかけることができます。",
        "連絡先名称": "岩崎交番",
        "電話番号": "0561-39-0110",
        "Webサイト": ""
      },
      "geometry": {
        "type": "Point",
        "coordinates": [
          137.043122367197,
          35.1442641459566
        ]
      }
    },
    {
      "type": "Feature",
      "properties": {
        "﻿全国地方公共団体コード": "23230",
        "識別値": "POK002",
        "種別": "交番",
        "name": "米野木交番",
        "施設名称（カナ）": "コメノキコウバン",
        "通称": "",
        "住所表記": "愛知県日進市米野木町仲田56-1",
        "郵便番号": "4700111",
        "description": "交番への連絡は愛知警察署の交換（0561-39-0110）を通じて電話をかけることができます。",
        "連絡先名称": "米野木交番",
        "電話番号": "0561-39-0110",
        "Webサイト": ""
      },
      "geometry": {
        "type": "Point",
        "coordinates": [
          137.061457027005,
          35.1325898833177
        ]
      }
    },
    {
      "type": "Feature",
      "properties": {
        "﻿全国地方公共団体コード": "23230",
        "識別値": "POK003",
        "種別": "交番",
        "name": "浅田交番",
        "施設名称（カナ）": "アサダコウバン",
        "通称": "",
        "住所表記": "愛知県日進市浅田町東前田44-3",
        "郵便番号": "4700124",
        "description": "交番への連絡は愛知警察署の交換（0561-39-0110）を通じて電話をかけることができます。",
        "連絡先名称": "浅田交番",
        "電話番号": "0561-39-0110",
        "Webサイト": ""
      },
      "geometry": {
        "type": "Point",
        "coordinates": [
          137.02382012017,
          35.1249403949495
        ]
      }
    }
  ]
};